fork_sanic_openapi-0.5.1.dist-info/DESCRIPTION.rst
fork_sanic_openapi-0.5.1.dist-info/METADATA
fork_sanic_openapi-0.5.1.dist-info/RECORD
fork_sanic_openapi-0.5.1.dist-info/WHEEL
fork_sanic_openapi-0.5.1.dist-info/metadata.json
fork_sanic_openapi-0.5.1.dist-info/top_level.txt
sanic_openapi/__init__.py
sanic_openapi/doc.py
sanic_openapi/openapi.py
sanic_openapi/swagger.py
sanic_openapi/ui/favicon-16x16.png
sanic_openapi/ui/favicon-32x32.png
sanic_openapi/ui/index.html
sanic_openapi/ui/oauth2-redirect.html
sanic_openapi/ui/swagger-ui-bundle.js
sanic_openapi/ui/swagger-ui-bundle.js.map
sanic_openapi/ui/swagger-ui-standalone-preset.js
sanic_openapi/ui/swagger-ui-standalone-preset.js.map
sanic_openapi/ui/swagger-ui.css
sanic_openapi/ui/swagger-ui.css.map
sanic_openapi/ui/swagger-ui.js
sanic_openapi/ui/swagger-ui.js.map
