Metadata-Version: 2.0
Name: fork-sanic-openapi
Version: 0.5.1
Summary: Fork of OpenAPI support for Sanic
Home-page: http://github.com/matsurihime/fork-sanic-openapi/
Author: matsurihime
Author-email: pipikapu@gmail.com
License: MIT
Platform: any
Classifier: Development Status :: 2 - Pre-Alpha
Classifier: Environment :: Web Environment
Classifier: License :: OSI Approved :: MIT License
Classifier: Programming Language :: Python :: 3.5
Classifier: Programming Language :: Python :: 3.6
Requires-Dist: sanic (>=0.6.0)
